{"type":"FeatureCollection","features":[{"type":"Feature","geometry":{"type":"Point","coordinates":[114.23558813,22.27866138]},"properties":{"GMID":"iVskL5Igcb","Northing":815534.0,"Easting":842319.0,"Dataset":"Horse Riding Schools","Facility Name":"Lei Yue Mun Public Riding School","Address":"75 Chai Wan Road, Chai Wan","數據集":"騎術學校","設施名稱":"鯉魚門公眾騎術學校","地址":"柴灣柴灣道七十五號","District":"EASTERN","地區":"東區","Opening Hours":"N.A.","開放時間":"N.A.","Telephone":"N.A.","聯絡電話":"N.A.","Fax Number":"N.A.","傳真號碼":"N.A.","Email Address":"N.A.","電郵地址":"N.A.","Website":"https://www.lcsd.gov.hk/en/prs/lym.html","網頁":"https://www.lcsd.gov.hk/tc/prs/lym.html","Last Update":"2021-11-23 04:39:36"}},{"type":"Feature","geometry":{"type":"Point","coordinates":[113.95858493,22.37592422]},"properties":{"GMID":"RebFSYJoAm","Northing":826319.0,"Easting":813786.0,"Dataset":"Horse Riding Schools","Facility Name":"Tuen Mun Public Riding School","Address":"Lot No. 45, Lung Mun Road, Tuen Mun","數據集":"騎術學校","設施名稱":"屯門公眾騎術學校","地址":"屯門龍門路四十五號地段","District":"TUEN MUN","地區":"屯門","Opening Hours":"","開放時間":"","Telephone":"","聯絡電話":"","Fax Number":"","傳真號碼":"","Email Address":"","電郵地址":"","Website":"http://www.lcsd.gov.hk/lschemes/prs/en/tm.php","網頁":"http://www.lcsd.gov.hk/lschemes/prs/b5/tm.php","Last Update":"2009-09-21 06:15:36"}}]}