{"type":"FeatureCollection","features":[{"type":"Feature","geometry":{"type":"Point","coordinates":[114.25864973,22.20704719]},"properties":{"GMID":"5IN59L9Mpy","Northing":807605.0,"Easting":844700.0,"Dataset":"Marine Reserve","Facility Name":"Cape D\u0027Aguilar Marine Reserve","Address":"Cape D\u0027Aguilar","數據集":"海岸保護區","設施名稱":"鶴咀海岸保護區","地址":"鶴咀","Telephone":"1823","聯絡電話":"1823","Fax Number":"N.A.","傳真號碼":"N.A.","Opening Hours":"N.A.","開放時間":"N.A.","Email Address":"N.A.","電郵地址":"N.A.","Website":"http://www.afcd.gov.hk/english/country/cou_vis/cou_vis_mar/cou_vis_mar_des/cou_vis_mar_des.html","網頁":"https://www.afcd.gov.hk/tc_chi/country/cou_vis/cou_vis_mar/cou_vis_mar_des/cou_vis_mar_des.html","Last Update":"2020-04-01 01:22:31"}}]}