{"type":"FeatureCollection","features":[{"type":"Feature","geometry":{"type":"Point","coordinates":[114.16526372,22.27858468]},"properties":{"GMID":"YrTRt84o2K","Northing":815524.0,"Easting":835071.0,"Dataset":"Public Vehicles Unit","Facility Name":"TRANSPORT DEPARTMENT PUBLIC VEHICLES UNIT","Address":"3/F, UNITED CENTRE, 95 QUEENSWAY, HONG KONG","數據集":"公共車輛分組","設施名稱":"運輸署公共車輛分組","地址":"香港金鐘道九十五號統一中心三樓","Opening Hours":"09:00 to 13:00\u003cbr/\u003e14:00 to 17:45\u003cbr/\u003e(Mondays to Fridays, except Public Holidays)","開放時間":"上午九時正至下午一時正\u003cbr/\u003e下午二時正至下午五時四十五分\u003cbr/\u003e(星期一至星期五，公眾假期除外)","Telephone":"Non-franchised Public Bus: (852) 2804 2574\u003cbr/\u003eNon-franchised Private Bus: (852) 2804 2450\u003cbr/\u003ePublic Light Bus: (852) 2804 2500\u003cbr/\u003ePrivate Light Bus \u0026 Hire Car: (852) 2804 2263\u003cbr/\u003eTaxi\t(852): 2804 2450","聯絡電話":"非專營公共巴士: (852)2804 2574\u003cbr/\u003e非專營私家巴士: (852)2804 2450\u003cbr/\u003e公共小巴: (852)2804 2500\u003cbr/\u003e私家小巴及出租汽車: (852)2804 2263\u003cbr/\u003e的士: (852)2804 2450","Fax Number":"(852)2865 1227","傳真號碼":"(852)2865 1227","Email Address":"","電郵地址":"","Website":"","網頁":"","Last Update":"2022-04-21 06:42:38"}}]}