{"type":"FeatureCollection","features":[{"type":"Feature","geometry":{"type":"Point","coordinates":[114.17266322,22.27738058]},"properties":{"GMID":"iUkGzzdRcS","Northing":815391.0,"Easting":835834.0,"Dataset":"Race Relations Unit, Home Affairs Department","Facility Name":"Race Relations Unit, Home Affairs Department","Address":"15/F, Southorn Centre, 130 Hennessy Road, Wan Chai, Hong Kong","數據集":"民政事務總署種族關係組","設施名稱":"民政事務總署種族關係組","地址":"香港灣仔軒尼詩道130號修頓中心15樓","District":"WAN CHAI","地區":"灣仔區","Opening Hours":"Mon - Fri: 8:45 am - 6:00 pm (Lunch Break 1:00 pm - 2:00 pm)","開放時間":"星期一至五: 上午8:45 - 下午6:00 (下午1:00 - 2:00午膳休息)","Telephone":"2835-1747","聯絡電話":"2835-1747","Fax Number":"2127-1716","傳真號碼":"2127-1716","Email Address":"rru_general_enquiry@had.gov.hk","電郵地址":"rru_general_enquiry@had.gov.hk","Website":"http://www.had.gov.hk/rru","網頁":"http://www.had.gov.hk/rru","Last Update":"2013-05-28 07:17:05"}}]}