{"features":[{"geometry":{"coordinates":[114.236465598929,22.2935097443977],"type":"Point"},"type":"Feature","properties":{"executionYear":"2017","executionDateZH":"2017年8月16日","locationZH":"油塘四山街 13及15號","relevantDistrictCouncilZH":"觀塘","maxResidentialGFAZH":"21,448","premiumEN":"983,030,000","premiumZH":"983,030,000","userZH":"住宅","maxResidentialGFAEN":"21,448","lotNumberZH":"油塘內地段 第41號","locationEN":"13 & 15, Sze Shan Street, Yau Tong","registrationDateZH":"2017年9月11日","lotNumberEN":"YTIL 41","relevantDistrictCouncilEN":"KWUN TONG","registrationDateEN":"11 September 2017","executionDateEN":"16 Aug 2017","userEN":"RESIDENTIAL"}},{"geometry":{"coordinates":[114.162390653014,22.2482832143479],"type":"Point"},"type":"Feature","properties":{"executionYear":"2014","executionDateZH":"2014年5月8日","locationZH":"黃竹坑黃竹坑道","relevantDistrictCouncilZH":"南區","maxResidentialGFAZH":"不適用","premiumEN":"1,069,730,000","premiumZH":"1,069,730,000","userZH":"非住宅用途","maxResidentialGFAEN":"N/A","lotNumberZH":"香港仔內地段第 461 號","locationEN":"Wong Chuk Hang Road, Wong Chuk Hang","registrationDateZH":"2014年5月20日","lotNumberEN":"AIL 461","relevantDistrictCouncilEN":"SOUTHERN","registrationDateEN":"20 May 2014","executionDateEN":"8 May 2014","userEN":"NON RESIDENTIAL"}},{"geometry":{"coordinates":[114.219957415916,22.3137412084829],"type":"Point"},"type":"Feature","properties":{"executionYear":"2014","executionDateZH":"2014年3月17日","locationZH":"觀塘創業街 15-17 號","relevantDistrictCouncilZH":"觀塘","maxResidentialGFAZH":"不適用","premiumEN":"1,121,710,000","premiumZH":"1,121,710,000","userZH":"非住宅用途","maxResidentialGFAEN":"N/A","lotNumberZH":"觀塘內地段 第 760 號","locationEN":"15-17 Chong Yip Street, Kwun Tong","registrationDateZH":"2014年4月2日","lotNumberEN":"KTIL 760","relevantDistrictCouncilEN":"KWUN TONG","registrationDateEN":"2 April 2014","executionDateEN":"17 Mar 2014","userEN":"NON RESIDENTIAL"}}],"type":"FeatureCollection"}