{"type":"FeatureCollection","features":[{"type":"Feature","geometry":{"type":"Point","coordinates":[114.17266322,22.27738058]},"properties":{"GMID":"XSTBbAz2Ua","Northing":815391.0,"Easting":835834.0,"Dataset":"Senior Citizen Card Office","Facility Name":"Senior Citizen Card Office","Address":"Room 2204, 22/F., Southorn Centre, 130 Hennessy Road, Wan Chai, Hong Kong","數據集":"長者咭辦事處","設施名稱":"長者咭辦事處","地址":"香港灣仔軒尼詩道130號修頓中心22樓2204室","Opening Hours":"Monday to Friday:8:45am to 1:00pm \u0026 2:00pm to 6:00pm<br/>Saturday, Sunday and Public Holidays :Closed","開放時間":"星期一至五:<br/>上午八時四十五分至下午一時 <br/>下午二時至下午六時<br/>星期六、日及公眾假期:休息","Telephone":"3583 2959","聯絡電話":"3583 2959","Fax Number":"25730079","傳真號碼":"25730079","Email Address":"sccoenq@swd.gov.hk","電郵地址":"N.A.","Website":"N.A.","網頁":"N.A.","Last Update":"2018-01-31 02:59:04"}}]}